basin3d/__init__.py
basin3d/monitor.py
basin3d/synthesis.py
basin3d/core/__init__.py
basin3d/core/access.py
basin3d/core/catalog.py
basin3d/core/connection.py
basin3d/core/logging.yaml
basin3d/core/models.py
basin3d/core/monitor.py
basin3d/core/plugin.py
basin3d/core/sqlalchemy_models.py
basin3d/core/synthesis.py
basin3d/core/translate.py
basin3d/core/types.py
basin3d/core/schema/__init__.py
basin3d/core/schema/enum.py
basin3d/core/schema/query.py
basin3d/data/__init__.py
basin3d/data/basin3d_observed_property_vocabulary.csv
basin3d/plugins/__init__.py
basin3d/plugins/epa.py
basin3d/plugins/epa_mapping.csv
basin3d/plugins/essdive.py
basin3d/plugins/essdive_mapping.csv
basin3d/plugins/usgs.py
basin3d/plugins/usgs_huc_codes.py
basin3d/plugins/usgs_mapping.csv
basin3d-1.3.0.dist-info/licenses/LICENSE
basin3d-1.3.0.dist-info/METADATA
basin3d-1.3.0.dist-info/WHEEL
basin3d-1.3.0.dist-info/top_level.txt
basin3d-1.3.0.dist-info/RECORD
